{
  "code": 200,
  "data": {
    "description": "",
    "html": "<html><head><meta name=\"color-scheme\" content=\"light dark\"></head><body><pre style=\"word-wrap: break-word; white-space: pre-wrap;\">{\n  \"id\": 740622069,\n  \"node_id\": \"R_kgDOLCT-9Q\",\n  \"name\": \"movie-api\",\n  \"full_name\": \"luismiguelro/movie-api\",\n  \"private\": false,\n  \"owner\": {\n    \"login\": \"luismiguelro\",\n    \"id\": 101124184,\n    \"node_id\": \"U_kgDOBgcIWA\",\n    \"avatar_url\": \"https://avatars.githubusercontent.com/u/101124184?v=4\",\n    \"gravatar_id\": \"\",\n    \"url\": \"https://api.github.com/users/luismiguelro\",\n    \"html_url\": \"https://github.com/luismiguelro\",\n    \"followers_url\": \"https://api.github.com/users/luismiguelro/followers\",\n    \"following_url\": \"https://api.github.com/users/luismiguelro/following{/other_user}\",\n    \"gists_url\": \"https://api.github.com/users/luismiguelro/gists{/gist_id}\",\n    \"starred_url\": \"https://api.github.com/users/luismiguelro/starred{/owner}{/repo}\",\n    \"subscriptions_url\": \"https://api.github.com/users/luismiguelro/subscriptions\",\n    \"organizations_url\": \"https://api.github.com/users/luismiguelro/orgs\",\n    \"repos_url\": \"https://api.github.com/users/luismiguelro/repos\",\n    \"events_url\": \"https://api.github.com/users/luismiguelro/events{/privacy}\",\n    \"received_events_url\": \"https://api.github.com/users/luismiguelro/received_events\",\n    \"type\": \"User\",\n    \"user_view_type\": \"public\",\n    \"site_admin\": false\n  },\n  \"html_url\": \"https://github.com/luismiguelro/movie-api\",\n  \"description\": \"REST API powered by Spring Boot\",\n  \"fork\": false,\n  \"url\": \"https://api.github.com/repos/luismiguelro/movie-api\",\n  \"forks_url\": \"https://api.github.com/repos/luismiguelro/movie-api/forks\",\n  \"keys_url\": \"https://api.github.com/repos/luismiguelro/movie-api/keys{/key_id}\",\n  \"collaborators_url\": \"https://api.github.com/repos/luismiguelro/movie-api/collaborators{/collaborator}\",\n  \"teams_url\": \"https://api.github.com/repos/luismiguelro/movie-api/teams\",\n  \"hooks_url\": \"https://api.github.com/repos/luismiguelro/movie-api/hooks\",\n  \"issue_events_url\": \"https://api.github.com/repos/luismiguelro/movie-api/issues/events{/number}\",\n  \"events_url\": \"https://api.github.com/repos/luismiguelro/movie-api/events\",\n  \"assignees_url\": \"https://api.github.com/repos/luismiguelro/movie-api/assignees{/user}\",\n  \"branches_url\": \"https://api.github.com/repos/luismiguelro/movie-api/branches{/branch}\",\n  \"tags_url\": \"https://api.github.com/repos/luismiguelro/movie-api/tags\",\n  \"blobs_url\": \"https://api.github.com/repos/luismiguelro/movie-api/git/blobs{/sha}\",\n  \"git_tags_url\": \"https://api.github.com/repos/luismiguelro/movie-api/git/tags{/sha}\",\n  \"git_refs_url\": \"https://api.github.com/repos/luismiguelro/movie-api/git/refs{/sha}\",\n  \"trees_url\": \"https://api.github.com/repos/luismiguelro/movie-api/git/trees{/sha}\",\n  \"statuses_url\": \"https://api.github.com/repos/luismiguelro/movie-api/statuses/{sha}\",\n  \"languages_url\": \"https://api.github.com/repos/luismiguelro/movie-api/languages\",\n  \"stargazers_url\": \"https://api.github.com/repos/luismiguelro/movie-api/stargazers\",\n  \"contributors_url\": \"https://api.github.com/repos/luismiguelro/movie-api/contributors\",\n  \"subscribers_url\": \"https://api.github.com/repos/luismiguelro/movie-api/subscribers\",\n  \"subscription_url\": \"https://api.github.com/repos/luismiguelro/movie-api/subscription\",\n  \"commits_url\": \"https://api.github.com/repos/luismiguelro/movie-api/commits{/sha}\",\n  \"git_commits_url\": \"https://api.github.com/repos/luismiguelro/movie-api/git/commits{/sha}\",\n  \"comments_url\": \"https://api.github.com/repos/luismiguelro/movie-api/comments{/number}\",\n  \"issue_comment_url\": \"https://api.github.com/repos/luismiguelro/movie-api/issues/comments{/number}\",\n  \"contents_url\": \"https://api.github.com/repos/luismiguelro/movie-api/contents/{+path}\",\n  \"compare_url\": \"https://api.github.com/repos/luismiguelro/movie-api/compare/{base}...{head}\",\n  \"merges_url\": \"https://api.github.com/repos/luismiguelro/movie-api/merges\",\n  \"archive_url\": \"https://api.github.com/repos/luismiguelro/movie-api/{archive_format}{/ref}\",\n  \"downloads_url\": \"https://api.github.com/repos/luismiguelro/movie-api/downloads\",\n  \"issues_url\": \"https://api.github.com/repos/luismiguelro/movie-api/issues{/number}\",\n  \"pulls_url\": \"https://api.github.com/repos/luismiguelro/movie-api/pulls{/number}\",\n  \"milestones_url\": \"https://api.github.com/repos/luismiguelro/movie-api/milestones{/number}\",\n  \"notifications_url\": \"https://api.github.com/repos/luismiguelro/movie-api/notifications{?since,all,participating}\",\n  \"labels_url\": \"https://api.github.com/repos/luismiguelro/movie-api/labels{/name}\",\n  \"releases_url\": \"https://api.github.com/repos/luismiguelro/movie-api/releases{/id}\",\n  \"deployments_url\": \"https://api.github.com/repos/luismiguelro/movie-api/deployments\",\n  \"created_at\": \"2024-01-08T18:09:21Z\",\n  \"updated_at\": \"2024-09-02T02:30:09Z\",\n  \"pushed_at\": \"2024-06-15T14:08:35Z\",\n  \"git_url\": \"git://github.com/luismiguelro/movie-api.git\",\n  \"ssh_url\": \"git@github.com:luismiguelro/movie-api.git\",\n  \"clone_url\": \"https://github.com/luismiguelro/movie-api.git\",\n  \"svn_url\": \"https://github.com/luismiguelro/movie-api\",\n  \"homepage\": \"https://api-movies.fly.dev\",\n  \"size\": 8740,\n  \"stargazers_count\": 2,\n  \"watchers_count\": 2,\n  \"language\": \"Java\",\n  \"has_issues\": true,\n  \"has_projects\": true,\n  \"has_downloads\": true,\n  \"has_wiki\": true,\n  \"has_pages\": false,\n  \"has_discussions\": false,\n  \"forks_count\": 0,\n  \"mirror_url\": null,\n  \"archived\": false,\n  \"disabled\": false,\n  \"open_issues_count\": 0,\n  \"license\": {\n    \"key\": \"mit\",\n    \"name\": \"MIT License\",\n    \"spdx_id\": \"MIT\",\n    \"url\": \"https://api.github.com/licenses/mit\",\n    \"node_id\": \"MDc6TGljZW5zZTEz\"\n  },\n  \"allow_forking\": true,\n  \"is_template\": false,\n  \"web_commit_signoff_required\": false,\n  \"has_pull_requests\": true,\n  \"pull_request_creation_policy\": \"all\",\n  \"topics\": [\n    \"api\",\n    \"flyio\",\n    \"spring-boot\"\n  ],\n  \"visibility\": \"public\",\n  \"forks\": 0,\n  \"open_issues\": 0,\n  \"watchers\": 2,\n  \"default_branch\": \"main\",\n  \"temp_clone_token\": null,\n  \"network_count\": 0,\n  \"subscribers_count\": 1\n}\n</pre></body></html>",
    "publishedTime": "Mon, 02 Sep 2024 02:30:09 GMT",
    "title": "",
    "url": "https://api.github.com/repos/luismiguelro/movie-api",
    "usage": {
      "tokens": 1867
    }
  },
  "meta": {
    "usage": {
      "tokens": 1867
    }
  },
  "status": 20000
}